dict_tools/__init__.py
dict_tools/aggregation.py
dict_tools/args.py
dict_tools/data.py
dict_tools/differ.py
dict_tools/mysql.py
dict_tools/trim.py
dict_tools/typing.py
dict_tools/update.py
dict_tools/utils.py
dict_tools/xml.py
dict_tools/yamlex.py
dict_toolbox-5.0.0.dist-info/LICENSE
dict_toolbox-5.0.0.dist-info/METADATA
dict_toolbox-5.0.0.dist-info/WHEEL
dict_toolbox-5.0.0.dist-info/top_level.txt
dict_toolbox-5.0.0.dist-info/RECORD
