Metadata-Version: 2.1
Name: dict-toolbox
Version: 5.0.0
Summary: Dict tools for Python projects
Home-page: https://gitlab.com/saltstack/open/dict-toolbox
Author: Tyler Johnson
Author-email: tyjohnson@vmware.com
Classifier: Environment :: Console
Classifier: Intended Audience :: Developers
Classifier: Intended Audience :: Information Technology
Classifier: Intended Audience :: System Administrators
Classifier: Operating System :: OS Independent
Classifier: Programming Language :: Python
Classifier: Programming Language :: Python :: 3.8
Classifier: Programming Language :: Python :: 3.9
Classifier: Programming Language :: Python :: 3.10
Classifier: Programming Language :: Python :: 3.11
Classifier: Development Status :: 5 - Production/Stable
Requires-Python: >=3.8
License-File: LICENSE
Requires-Dist: aiofiles>=0.7.0
Requires-Dist: msgpack!=0.5.5,>=0.5
Requires-Dist: pyYAML>=6.0.1
